sixdrepnet/__init__.py
sixdrepnet/convert.py
sixdrepnet/create_filename_list.py
sixdrepnet/datasets.py
sixdrepnet/demo.py
sixdrepnet/loss.py
sixdrepnet/model.py
sixdrepnet/regressor.py
sixdrepnet/test.py
sixdrepnet/train.py
sixdrepnet/utils.py
sixdrepnet/backbone/__init__.py
sixdrepnet/backbone/repvgg.py
sixdrepnet/backbone/se_block.py
sixdrepnet-0.1.6.dist-info/LICENSE
sixdrepnet-0.1.6.dist-info/METADATA
sixdrepnet-0.1.6.dist-info/WHEEL
sixdrepnet-0.1.6.dist-info/top_level.txt
sixdrepnet-0.1.6.dist-info/RECORD
