Metadata-Version: 2.1
Name: sixdrepnet
Version: 0.1.6
Summary: Efficient and accurate image-based head pose estimation
Home-page: https://github.com/thohemp/6DRepNet
Author: Thorsten Hempel
Author-email: thorsten.hempel@ovgu.de
License: MIT
Platform: UNKNOWN
Classifier: Programming Language :: Python :: 3
Classifier: Intended Audience :: Science/Research
Classifier: License :: OSI Approved :: MIT License
Classifier: Operating System :: OS Independent
License-File: LICENSE
Requires-Dist: Pillow (>=8.4.0)
Requires-Dist: matplotlib (>=3.3.4)
Requires-Dist: numpy (>=1.19.5)
Requires-Dist: opencv-python (>=4.5.5)
Requires-Dist: pandas (>=1.1.5)
Requires-Dist: scipy (>=1.5.4)
Requires-Dist: torch (>=1.10.1)
Requires-Dist: torchvision (>=0.11.2)
